Verilog_projects/FFT_VS_MATLAB/trigos.v
`timescale 1ns/1ps

// Simple LUT for arctangent values (Q1.31 fixed point)
module lut_arctan(
    input  wire [4:0] idx,       // 0..31
    output reg  [31:0] atan_val
);
    always @(*) begin
        case(idx)
            5'd0:  atan_val = 32'h3243F6A9; // atan(2^-0) ≈ 45 deg
            5'd1:  atan_val = 32'h1DAC6705; // atan(2^-1)
            5'd2:  atan_val = 32'h0FADBAFC; // atan(2^-2)
            5'd3:  atan_val = 32'h07F56EA6;
            5'd4:  atan_val = 32'h03FEAB76;
            5'd5:  atan_val = 32'h01FFD55B;
            5'd6:  atan_val = 32'h00FFFABA;
            5'd7:  atan_val = 32'h007FFFD5;
            5'd8:  atan_val = 32'h003FFFFF;
            5'd9:  atan_val = 32'h001FFFFF;
            5'd10: atan_val = 32'h000FFFFF;
            5'd11: atan_val = 32'h0007FFFF;
            5'd12: atan_val = 32'h0003FFFF;
            5'd13: atan_val = 32'h0001FFFF;
            5'd14: atan_val = 32'h0000FFFF;
            5'd15: atan_val = 32'h00007FFF;
            default: atan_val = 32'h0;
        endcase
    end
endmodule


// Iterative CORDIC for cos and sin
module cordic_cos #(
    parameter WIDTH = 32,
    parameter ITER  = 16       // Number of iterations
)(
    input  wire                 clk,
    input  wire                 rst,
    input  wire [WIDTH-1:0]     angle_in,  // Q1.31 fixed-point
    output reg  [WIDTH-1:0]     cos_out,   // Q1.31
    output reg  [WIDTH-1:0]     sin_out    // Q1.31
);

    // Scaling factor K ≈ 0.607252 (Q1.31)
    localparam [WIDTH-1:0] K = 32'h4DBA76D0;

    // Iteration registers
    reg [WIDTH-1:0] x, y, z;
    reg [4:0] i;
    reg busy;

    wire [WIDTH-1:0] atan_val;
    lut_arctan arctan_lookup(.idx(i[4:0]), .atan_val(atan_val));

    always @(posedge clk or posedge rst) begin
        if (rst) begin
            x       <= 0;
            y       <= 0;
            z       <= 0;
            i       <= 0;
            busy    <= 0;
            cos_out <= 0;
            sin_out <= 0;
        end else begin
            if (!busy) begin
                // Initialize vector
                x    <= K;
                y    <= 0;
                z    <= angle_in;
                i    <= 0;
                busy <= 1;
            end else if (i < ITER) begin
                // Rotation
                if (z[WIDTH-1] == 0) begin // z >= 0
                    x <= x - (y >>> i);
                    y <= y + (x >>> i);
                    z <= z - atan_val;
                end else begin
                    x <= x + (y >>> i);
                    y <= y - (x >>> i);
                    z <= z + atan_val;
                end
                i <= i + 1;
            end else begin
                // Done
                cos_out <= x;
                sin_out <= y;
                busy <= 0;
            end
        end
    end

endmodule

Verilog_projects/FFT_VS_MATLAB/fft.v
`timescale 1ns/1ps

module fft #(
    parameter WIDTH = 32,
    parameter N     = 8,
    parameter LOG2N = 3,
    parameter ITER  = 16  // CORDIC iterations
)(
    input  wire                  clk,
    input  wire                  rst,
    input  wire signed [WIDTH-1:0] x_r [0:N-1],
    input  wire signed [WIDTH-1:0] x_i [0:N-1],
    output reg  signed [WIDTH-1:0] X_r [0:N-1],
    output reg  signed [WIDTH-1:0] X_i [0:N-1]
);

    // Internal registers
    integer i, s, k, j;
    reg signed [WIDTH-1:0] u_r, u_i;
    reg signed [WIDTH-1:0] t_r, t_i;

    // Twiddle angle in Q1.31
    reg [31:0] angle_q31;

    // Sequential control
    reg [LOG2N:0] stage;
    reg [31:0] step;

    // CORDIC outputs
    reg start_cordic;
    wire [WIDTH-1:0] cos_val;
    wire [WIDTH-1:0] sin_val;
    wire busy;

    cordic_cos #(
        .WIDTH(WIDTH),
        .ITER(ITER)
    ) cordic_inst (
        .clk(clk),
        .rst(rst),
        .angle_in(angle_q31),
        .cos_out(cos_val),
        .sin_out(sin_val)
    );

    always @(posedge clk or posedge rst) begin
        if (rst) begin
            stage <= 0;
            step  <= 0;
            start_cordic <= 0;

            for (i = 0; i < N; i = i + 1) begin
                X_r[i] <= x_r[i];
                X_i[i] <= x_i[i];
            end
        end else begin
            // Sequential FFT computation
            for (s = 1; s <= LOG2N; s = s + 1) begin
                integer m = 1 << s;

                for (k = 0; k < N; k = k + m) begin
                    for (j = 0; j < m/2; j = j + 1) begin
                        // Compute twiddle angle θ = -2π j / m in Q1.31
                        angle_q31 <= (32'sd2147483647 * (-2 * 3_14159265 * j / m));

                        // Wait for CORDIC to finish
                        if (!busy) begin
                            u_r = X_r[k + j];
                            u_i = X_i[k + j];

                            t_r = (cos_val * X_r[k + j + m/2] - sin_val * X_i[k + j + m/2]) >>> 31;
                            t_i = (cos_val * X_i[k + j + m/2] + sin_val * X_r[k + j + m/2]) >>> 31;

                            // Update butterfly
                            X_r[k + j]       <= u_r + t_r;
                            X_i[k + j]       <= u_i + t_i;
                            X_r[k + j + m/2] <= u_r - t_r;
                            X_i[k + j + m/2] <= u_i - t_i;
                        end
                    end
                end
            end
        end
    end

endmodule

Verilog_projects/FFT_VS_MATLAB/tb_fft.v
`timescale 1ns/1ps

module fft_tb;

    localparam WIDTH = 32;
    localparam N     = 8;
    localparam LOG2N = 3;

    reg clk;
    reg rst;

    // Input arrays
    reg signed [WIDTH-1:0] x_r [0:N-1];
    reg signed [WIDTH-1:0] x_i [0:N-1];

    // FFT output arrays
    wire signed [WIDTH-1:0] X_r [0:N-1];
    wire signed [WIDTH-1:0] X_i [0:N-1];

    integer i;

    // Flattened registers for VCD dumping
    reg signed [WIDTH-1:0] X_R_flat0, X_R_flat1, X_R_flat2, X_R_flat3,
                           X_R_flat4, X_R_flat5, X_R_flat6, X_R_flat7;

    reg signed [WIDTH-1:0] X_I_flat0, X_I_flat1, X_I_flat2, X_I_flat3,
                           X_I_flat4, X_I_flat5, X_I_flat6, X_I_flat7;

    // LUTs for test signal
    reg signed [WIDTH-1:0] cos_lut [0:N-1];
    reg signed [WIDTH-1:0] sin_lut [0:N-1];

    // Instantiate FFT
    fft #(
        .WIDTH(WIDTH),
        .N(N),
        .LOG2N(LOG2N)
    ) uut (
        .clk(clk),
        .rst(rst),
        .x_r(x_r),
        .x_i(x_i),
        .X_r(X_r),
        .X_i(X_i)
    );

    // Clock generation
    initial begin
        clk = 0;
        forever #5 clk = ~clk;
    end

    // Assign flattened outputs for VCD
    always @(*) begin
        X_R_flat0 = X_r[0]; X_R_flat1 = X_r[1]; X_R_flat2 = X_r[2]; X_R_flat3 = X_r[3];
        X_R_flat4 = X_r[4]; X_R_flat5 = X_r[5]; X_R_flat6 = X_r[6]; X_R_flat7 = X_r[7];

        X_I_flat0 = X_i[0]; X_I_flat1 = X_i[1]; X_I_flat2 = X_i[2]; X_I_flat3 = X_i[3];
        X_I_flat4 = X_i[4]; X_I_flat5 = X_i[5]; X_I_flat6 = X_i[6]; X_I_flat7 = X_i[7];
    end

    // Initialize LUTs and inputs
    initial begin
        rst = 1;

        // Example: cos[n] + j*sin[n] test signal
        cos_lut[0] = 32'sd2147483647;  sin_lut[0] = 32'sd0;
        cos_lut[1] = 32'sd1518500249;  sin_lut[1] = 32'sd1518500249;
        cos_lut[2] = 32'sd0;           sin_lut[2] = 32'sd2147483647;
        cos_lut[3] = -32'sd1518500249; sin_lut[3] = 32'sd1518500249;
        cos_lut[4] = -32'sd2147483647; sin_lut[4] = 32'sd0;
        cos_lut[5] = -32'sd1518500249; sin_lut[5] = -32'sd1518500249;
        cos_lut[6] = 32'sd0;           sin_lut[6] = -32'sd2147483647;
        cos_lut[7] = 32'sd1518500249;  sin_lut[7] = -32'sd1518500249;

        for (i = 0; i < N; i = i + 1) begin
            x_r[i] = cos_lut[i];
            x_i[i] = sin_lut[i];
        end

        #20;
        rst = 0;

        // Wait enough cycles for sequential FFT + CORDIC
        #2000;

        // Display FFT output
        $display("FFT Output:");
        for (i = 0; i < N; i = i + 1) begin
            $display("X[%0d] = %0d + j%0d", i, X_r[i], X_i[i]);
        end

        #20;
        $finish;
    end

    // VCD dump
    initial begin
        $dumpfile("fft_tb.vcd");

        // Dump entire testbench
        $dumpvars(0, fft_tb);

        // Dump flattened FFT outputs
        $dumpvars(0, fft_tb.X_R_flat0);
        $dumpvars(0, fft_tb.X_R_flat1);
        $dumpvars(0, fft_tb.X_R_flat2);
        $dumpvars(0, fft_tb.X_R_flat3);
        $dumpvars(0, fft_tb.X_R_flat4);
        $dumpvars(0, fft_tb.X_R_flat5);
        $dumpvars(0, fft_tb.X_R_flat6);
        $dumpvars(0, fft_tb.X_R_flat7);

        $dumpvars(0, fft_tb.X_I_flat0);
        $dumpvars(0, fft_tb.X_I_flat1);
        $dumpvars(0, fft_tb.X_I_flat2);
        $dumpvars(0, fft_tb.X_I_flat3);
        $dumpvars(0, fft_tb.X_I_flat4);
        $dumpvars(0, fft_tb.X_I_flat5);
        $dumpvars(0, fft_tb.X_I_flat6);
        $dumpvars(0, fft_tb.X_I_flat7);
    end

endmodule

Verilog_projects/FFT_VS_MATLAB/fft_tb.vcd
$date
	Sun Dec 14 19:22:45 2025
$end
$version
	Icarus Verilog
$end
$timescale
	1ps
$end
$scope module fft_tb $end
$var parameter 32 ! LOG2N $end
$var parameter 32 " N $end
$var parameter 32 # WIDTH $end
$var reg 32 $ X_I_flat0 [31:0] $end
$var reg 32 % X_I_flat1 [31:0] $end
$var reg 32 & X_I_flat2 [31:0] $end
$var reg 32 ' X_I_flat3 [31:0] $end
$var reg 32 ( X_I_flat4 [31:0] $end
$var reg 32 ) X_I_flat5 [31:0] $end
$var reg 32 * X_I_flat6 [31:0] $end
$var reg 32 + X_I_flat7 [31:0] $end
$var reg 32 , X_R_flat0 [31:0] $end
$var reg 32 - X_R_flat1 [31:0] $end
$var reg 32 . X_R_flat2 [31:0] $end
$var reg 32 / X_R_flat3 [31:0] $end
$var reg 32 0 X_R_flat4 [31:0] $end
$var reg 32 1 X_R_flat5 [31:0] $end
$var reg 32 2 X_R_flat6 [31:0] $end
$var reg 32 3 X_R_flat7 [31:0] $end
$var reg 1 4 clk $end
$var reg 1 5 rst $end
$var integer 32 6 i [31:0] $end
$scope module uut $end
$var wire 1 7 busy $end
$var wire 1 4 clk $end
$var wire 1 5 rst $end
$var wire 32 8 sin_val [31:0] $end
$var wire 32 9 cos_val [31:0] $end
$var parameter 32 : ITER $end
$var parameter 32 ; LOG2N $end
$var parameter 32 < N $end
$var parameter 32 = WIDTH $end
$var reg 32 > angle_q31 [31:0] $end
$var reg 4 ? stage [3:0] $end
$var reg 1 @ start_cordic $end
$var reg 32 A step [31:0] $end
$var reg 32 B t_i [31:0] $end
$var reg 32 C t_r [31:0] $end
$var reg 32 D u_i [31:0] $end
$var reg 32 E u_r [31:0] $end
$var integer 32 F i [31:0] $end
$var integer 32 G j [31:0] $end
$var integer 32 H k [31:0] $end
$var integer 32 I s [31:0] $end
$scope module cordic_inst $end
$var wire 32 J angle_in [31:0] $end
$var wire 1 4 clk $end
$var wire 1 5 rst $end
$var wire 32 K atan_val [31:0] $end
$var parameter 32 L ITER $end
$var parameter 32 M K $end
$var parameter 32 N WIDTH $end
$var reg 1 O busy $end
$var reg 32 P cos_out [31:0] $end
$var reg 5 Q i [4:0] $end
$var reg 32 R sin_out [31:0] $end
$var reg 32 S x [31:0] $end
$var reg 32 T y [31:0] $end
$var reg 32 U z [31:0] $end
$scope module arctan_lookup $end
$var wire 5 V idx [4:0] $end
$var reg 32 W atan_val [31:0] $end
$upscope $end
$upscope $end
$scope begin $unm_blk_5 $end
$var integer 32 X m [31:0] $end
$upscope $end
$upscope $end
$upscope $end
$enddefinitions $end
$comment Show the parameter values. $end
$dumpall
b100000 N
b1001101101110100111011011010000 M
b10000 L
b100000 =
b1000 <
b11 ;
b10000 :
b100000 #
b1000 "
b11 !
$end
#0
$dumpvars
bx X
b110010010000111111011010101001 W
b0 V
b0 U
b0 T
b0 S
b0 R
b0 Q
b0 P
0O
b110010010000111111011010101001 K
bx J
bx I
bx H
bx G
b1000 F
bx E
bx D
bx C
bx B
b0 A
0@
b0 ?
bx >
b0 9
b0 8
z7
b1000 6
15
04
b1011010100000100111100110011001 3
b0 2
b10100101011111011000011001100111 1
b10000000000000000000000000000001 0
b10100101011111011000011001100111 /
b0 .
b1011010100000100111100110011001 -
b1111111111111111111111111111111 ,
b10100101011111011000011001100111 +
b10000000000000000000000000000001 *
b10100101011111011000011001100111 )
b0 (
b1011010100000100111100110011001 '
b1111111111111111111111111111111 &
b1011010100000100111100110011001 %
b0 $
$end
#5000
b1000 F
14
#10000
04
#15000
b1000 F
14
#20000
04
05
#25000
1O
bx U
b1001101101110100111011011010000 S
b0 G
bx H
b100 I
14
#30000
04
#35000
b11101101011000110011100000101 K
b11101101011000110011100000101 W
b1 Q
b1 V
b10110010010001011000100100110000 T
bx H
b100 I
14
#40000
04
#45000
b1111101011011011101011111100 K
b1111101011011011101011111100 W
b10 Q
b10 V
b10001011011010000100110111001000 T
b10100110110111010011101101101000 S
bx H
b100 I
14
#50000
04
#55000
b111111101010110111010100110 K
b111111101010110111010100110 W
b11 Q
b11 V
b1100001101100001111111011101110 T
b11001001101101110100111011011010 S
bx H
b100 I
14
#60000
04
#65000
b11111111101010101101110110 K
b11111111101010101101110110 W
b100 Q
b100 V
b1001000011110100001010100010011 T
b11010101111011010110111010110111 S
bx H
b100 I
14
#70000
04
#75000
b1111111111101010101011011 K
b1111111111101010101011011 W
b101 Q
b101 V
b111011000110110011111000101000 T
b11011010011101010001000000001000 S
bx H
b100 I
14
#80000
04
#85000
b111111111111101010111010 K
b111111111111101010111010 W
b110 Q
b110 V
b110100010001111001010110101000 T
b11011100010011011110100111111001 S
bx H
b100 I
14
#90000
04
#95000
b11111111111111111010101 K
b11111111111111111010101 W
b111 Q
b111 V
b110000110101100101111000000001 T
b11011101000111110000100001001111 S
bx H
b100 I
14
#100000
04
#105000
b1111111111111111111111 K
b1111111111111111111111 W
b1000 Q
b1000 V
b101111000111000001111111110001 T
b11011101100000001011010100001011 S
bx H
b100 I
14
#110000
04
#115000
b111111111111111111111 K
b111111111111111111111 W
b1001 Q
b1001 V
b101110001111101001111100111100 T
b11011101101011111101000100101010 S
bx H
b100 I
14
#120000
04
#125000
b11111111111111111111 K
b11111111111111111111 W
b1010 Q
b1010 V
b101101110011111100011101010100 T
b11011101110001101111000001111001 S
bx H
b100 I
14
#130000
04
#135000
b1111111111111111111 K
b1111111111111111111 W
b1011 Q
b1011 V
b101101100110000101010110011000 T
b11011101110100100110010001101010 S
bx H
b100 I
14
#140000
04
#145000
b111111111111111111 K
b111111111111111111 W
b1100 Q
b1100 V
b101101011111001001101101001100 T
b11011101110110000001011101110100 S
bx H
b100 I
14
#150000
04
#155000
b11111111111111111 K
b11111111111111111 W
b1101 Q
b1101 V
b101101011011101011110111001011 T
b11011101110110101110111100111101 S
bx H
b100 I
14
#160000
04
#165000
b1111111111111111 K
b1111111111111111 W
b1110 Q
b1110 V
b101101011001111100111011110100 T
b11011101110111000101101010110010 S
bx H
b100 I
14
#170000
04
#175000
b111111111111111 K
b111111111111111 W
b1111 Q
b1111 V
b101101011001000101011110000011 T
b11011101110111010001000001010001 S
bx H
b100 I
14
#180000
04
#185000
b0 K
b0 W
b10000 Q
b10000 V
b101101011000101001101111001001 T
b11011101110111010110101100011001 S
bx H
b100 I
14
#190000
04
#195000
0O
b101101011000101001101111001001 8
b101101011000101001101111001001 R
b11011101110111010110101100011001 9
b11011101110111010110101100011001 P
bx H
b100 I
14
#200000
04
#205000
b110010010000111111011010101001 K
b110010010000111111011010101001 W
1O
b0 Q
b0 V
b0 T
b1001101101110100111011011010000 S
bx H
b100 I
14
#210000
04
#215000
b11101101011000110011100000101 K
b11101101011000110011100000101 W
b1 Q
b1 V
b10110010010001011000100100110000 T
bx H
b100 I
14
#220000
04
#225000
b1111101011011011101011111100 K
b1111101011011011101011111100 W
b10 Q
b10 V
b10001011011010000100110111001000 T
b10100110110111010011101101101000 S
bx H
b100 I
14
#230000
04
#235000
b111111101010110111010100110 K
b111111101010110111010100110 W
b11 Q
b11 V
b1100001101100001111111011101110 T
b11001001101101110100111011011010 S
bx H
b100 I
14
#240000
04
#245000
b11111111101010101101110110 K
b11111111101010101101110110 W
b100 Q
b100 V
b1001000011110100001010100010011 T
b11010101111011010110111010110111 S
bx H
b100 I
14
#250000
04
#255000
b1111111111101010101011011 K
b1111111111101010101011011 W
b101 Q
b101 V
b111011000110110011111000101000 T
b11011010011101010001000000001000 S
bx H
b100 I
14
#260000
04
#265000
b111111111111101010111010 K
b111111111111101010111010 W
b110 Q
b110 V
b110100010001111001010110101000 T
b11011100010011011110100111111001 S
bx H
b100 I
14
#270000
04
#275000
b11111111111111111010101 K
b11111111111111111010101 W
b111 Q
b111 V
b110000110101100101111000000001 T
b11011101000111110000100001001111 S
bx H
b100 I
14
#280000
04
#285000
b1111111111111111111111 K
b1111111111111111111111 W
b1000 Q
b1000 V
b101111000111000001111111110001 T
b11011101100000001011010100001011 S
bx H
b100 I
14
#290000
04
#295000
b111111111111111111111 K
b111111111111111111111 W
b1001 Q
b1001 V
b101110001111101001111100111100 T
b11011101101011111101000100101010 S
bx H
b100 I
14
#300000
04
#305000
b11111111111111111111 K
b11111111111111111111 W
b1010 Q
b1010 V
b101101110011111100011101010100 T
b11011101110001101111000001111001 S
bx H
b100 I
14
#310000
04
#315000
b1111111111111111111 K
b1111111111111111111 W
b1011 Q
b1011 V
b101101100110000101010110011000 T
b11011101110100100110010001101010 S
bx H
b100 I
14
#320000
04
#325000
b111111111111111111 K
b111111111111111111 W
b1100 Q
b1100 V
b101101011111001001101101001100 T
b11011101110110000001011101110100 S
bx H
b100 I
14
#330000
04
#335000
b11111111111111111 K
b11111111111111111 W
b1101 Q
b1101 V
b101101011011101011110111001011 T
b11011101110110101110111100111101 S
bx H
b100 I
14
#340000
04
#345000
b1111111111111111 K
b1111111111111111 W
b1110 Q
b1110 V
b101101011001111100111011110100 T
b11011101110111000101101010110010 S
bx H
b100 I
14
#350000
04
#355000
b111111111111111 K
b111111111111111 W
b1111 Q
b1111 V
b101101011001000101011110000011 T
b11011101110111010001000001010001 S
bx H
b100 I
14
#360000
04
#365000
b0 K
b0 W
b10000 Q
b10000 V
b101101011000101001101111001001 T
b11011101110111010110101100011001 S
bx H
b100 I
14
#370000
04
#375000
0O
bx H
b100 I
14
#380000
04
#385000
b110010010000111111011010101001 K
b110010010000111111011010101001 W
1O
b0 Q
b0 V
b0 T
b1001101101110100111011011010000 S
bx H
b100 I
14
#390000
04
#395000
b11101101011000110011100000101 K
b11101101011000110011100000101 W
b1 Q
b1 V
b10110010010001011000100100110000 T
bx H
b100 I
14
#400000
04
#405000
b1111101011011011101011111100 K
b1111101011011011101011111100 W
b10 Q
b10 V
b10001011011010000100110111001000 T
b10100110110111010011101101101000 S
bx H
b100 I
14
#410000
04
#415000
b111111101010110111010100110 K
b111111101010110111010100110 W
b11 Q
b11 V
b1100001101100001111111011101110 T
b11001001101101110100111011011010 S
bx H
b100 I
14
#420000
04
#425000
b11111111101010101101110110 K
b11111111101010101101110110 W
b100 Q
b100 V
b1001000011110100001010100010011 T
b11010101111011010110111010110111 S
bx H
b100 I
14
#430000
04
#435000
b1111111111101010101011011 K
b1111111111101010101011011 W
b101 Q
b101 V
b111011000110110011111000101000 T
b11011010011101010001000000001000 S
bx H
b100 I
14
#440000
04
#445000
b111111111111101010111010 K
b111111111111101010111010 W
b110 Q
b110 V
b110100010001111001010110101000 T
b11011100010011011110100111111001 S
bx H
b100 I
14
#450000
04
#455000
b11111111111111111010101 K
b11111111111111111010101 W
b111 Q
b111 V
b110000110101100101111000000001 T
b11011101000111110000100001001111 S
bx H
b100 I
14
#460000
04
#465000
b1111111111111111111111 K
b1111111111111111111111 W
b1000 Q
b1000 V
b101111000111000001111111110001 T
b11011101100000001011010100001011 S
bx H
b100 I
14
#470000
04
#475000
b111111111111111111111 K
b111111111111111111111 W
b1001 Q
b1001 V
b101110001111101001111100111100 T
b11011101101011111101000100101010 S
bx H
b100 I
14
#480000
04
#485000
b11111111111111111111 K
b11111111111111111111 W
b1010 Q
b1010 V
b101101110011111100011101010100 T
b11011101110001101111000001111001 S
bx H
b100 I
14
#490000
04
#495000
b1111111111111111111 K
b1111111111111111111 W
b1011 Q
b1011 V
b101101100110000101010110011000 T
b11011101110100100110010001101010 S
bx H
b100 I
14
#500000
04
#505000
b111111111111111111 K
b111111111111111111 W
b1100 Q
b1100 V
b101101011111001001101101001100 T
b11011101110110000001011101110100 S
bx H
b100 I
14
#510000
04
#515000
b11111111111111111 K
b11111111111111111 W
b1101 Q
b1101 V
b101101011011101011110111001011 T
b11011101110110101110111100111101 S
bx H
b100 I
14
#520000
04
#525000
b1111111111111111 K
b1111111111111111 W
b1110 Q
b1110 V
b101101011001111100111011110100 T
b11011101110111000101101010110010 S
bx H
b100 I
14
#530000
04
#535000
b111111111111111 K
b111111111111111 W
b1111 Q
b1111 V
b101101011001000101011110000011 T
b11011101110111010001000001010001 S
bx H
b100 I
14
#540000
04
#545000
b0 K
b0 W
b10000 Q
b10000 V
b101101011000101001101111001001 T
b11011101110111010110101100011001 S
bx H
b100 I
14
#550000
04
#555000
0O
bx H
b100 I
14
#560000
04
#565000
b110010010000111111011010101001 K
b110010010000111111011010101001 W
1O
b0 Q
b0 V
b0 T
b1001101101110100111011011010000 S
bx H
b100 I
14
#570000
04
#575000
b11101101011000110011100000101 K
b11101101011000110011100000101 W
b1 Q
b1 V
b10110010010001011000100100110000 T
bx H
b100 I
14
#580000
04
#585000
b1111101011011011101011111100 K
b1111101011011011101011111100 W
b10 Q
b10 V
b10001011011010000100110111001000 T
b10100110110111010011101101101000 S
bx H
b100 I
14
#590000
04
#595000
b111111101010110111010100110 K
b111111101010110111010100110 W
b11 Q
b11 V
b1100001101100001111111011101110 T
b11001001101101110100111011011010 S
bx H
b100 I
14
#600000
04
#605000
b11111111101010101101110110 K
b11111111101010101101110110 W
b100 Q
b100 V
b1001000011110100001010100010011 T
b11010101111011010110111010110111 S
bx H
b100 I
14
#610000
04
#615000
b1111111111101010101011011 K
b1111111111101010101011011 W
b101 Q
b101 V
b111011000110110011111000101000 T
b11011010011101010001000000001000 S
bx H
b100 I
14
#620000
04
#625000
b111111111111101010111010 K
b111111111111101010111010 W
b110 Q
b110 V
b110100010001111001010110101000 T
b11011100010011011110100111111001 S
bx H
b100 I
14
#630000
04
#635000
b11111111111111111010101 K
b11111111111111111010101 W
b111 Q
b111 V
b110000110101100101111000000001 T
b11011101000111110000100001001111 S
bx H
b100 I
14
#640000
04
#645000
b1111111111111111111111 K
b1111111111111111111111 W
b1000 Q
b1000 V
b101111000111000001111111110001 T
b11011101100000001011010100001011 S
bx H
b100 I
14
#650000
04
#655000
b111111111111111111111 K
b111111111111111111111 W
b1001 Q
b1001 V
b101110001111101001111100111100 T
b11011101101011111101000100101010 S
bx H
b100 I
14
#660000
04
#665000
b11111111111111111111 K
b11111111111111111111 W
b1010 Q
b1010 V
b101101110011111100011101010100 T
b11011101110001101111000001111001 S
bx H
b100 I
14
#670000
04
#675000
b1111111111111111111 K
b1111111111111111111 W
b1011 Q
b1011 V
b101101100110000101010110011000 T
b11011101110100100110010001101010 S
bx H
b100 I
14
#680000
04
#685000
b111111111111111111 K
b111111111111111111 W
b1100 Q
b1100 V
b101101011111001001101101001100 T
b11011101110110000001011101110100 S
bx H
b100 I
14
#690000
04
#695000
b11111111111111111 K
b11111111111111111 W
b1101 Q
b1101 V
b101101011011101011110111001011 T
b11011101110110101110111100111101 S
bx H
b100 I
14
#700000
04
#705000
b1111111111111111 K
b1111111111111111 W
b1110 Q
b1110 V
b101101011001111100111011110100 T
b11011101110111000101101010110010 S
bx H
b100 I
14
#710000
04
#715000
b111111111111111 K
b111111111111111 W
b1111 Q
b1111 V
b101101011001000101011110000011 T
b11011101110111010001000001010001 S
bx H
b100 I
14
#720000
04
#725000
b0 K
b0 W
b10000 Q
b10000 V
b101101011000101001101111001001 T
b11011101110111010110101100011001 S
bx H
b100 I
14
#730000
04
#735000
0O
bx H
b100 I
14
#740000
04
#745000
b110010010000111111011010101001 K
b110010010000111111011010101001 W
1O
b0 Q
b0 V
b0 T
b1001101101110100111011011010000 S
bx H
b100 I
14
#750000
04
#755000
b11101101011000110011100000101 K
b11101101011000110011100000101 W
b1 Q
b1 V
b10110010010001011000100100110000 T
bx H
b100 I
14
#760000
04
#765000
b1111101011011011101011111100 K
b1111101011011011101011111100 W
b10 Q
b10 V
b10001011011010000100110111001000 T
b10100110110111010011101101101000 S
bx H
b100 I
14
#770000
04
#775000
b111111101010110111010100110 K
b111111101010110111010100110 W
b11 Q
b11 V
b1100001101100001111111011101110 T
b11001001101101110100111011011010 S
bx H
b100 I
14
#780000
04
#785000
b11111111101010101101110110 K
b11111111101010101101110110 W
b100 Q
b100 V
b1001000011110100001010100010011 T
b11010101111011010110111010110111 S
bx H
b100 I
14
#790000
04
#795000
b1111111111101010101011011 K
b1111111111101010101011011 W
b101 Q
b101 V
b111011000110110011111000101000 T
b11011010011101010001000000001000 S
bx H
b100 I
14
#800000
04
#805000
b111111111111101010111010 K
b111111111111101010111010 W
b110 Q
b110 V
b110100010001111001010110101000 T
b11011100010011011110100111111001 S
bx H
b100 I
14
#810000
04
#815000
b11111111111111111010101 K
b11111111111111111010101 W
b111 Q
b111 V
b110000110101100101111000000001 T
b11011101000111110000100001001111 S
bx H
b100 I
14
#820000
04
#825000
b1111111111111111111111 K
b1111111111111111111111 W
b1000 Q
b1000 V
b101111000111000001111111110001 T
b11011101100000001011010100001011 S
bx H
b100 I
14
#830000
04
#835000
b111111111111111111111 K
b111111111111111111111 W
b1001 Q
b1001 V
b101110001111101001111100111100 T
b11011101101011111101000100101010 S
bx H
b100 I
14
#840000
04
#845000
b11111111111111111111 K
b11111111111111111111 W
b1010 Q
b1010 V
b101101110011111100011101010100 T
b11011101110001101111000001111001 S
bx H
b100 I
14
#850000
04
#855000
b1111111111111111111 K
b1111111111111111111 W
b1011 Q
b1011 V
b101101100110000101010110011000 T
b11011101110100100110010001101010 S
bx H
b100 I
14
#860000
04
#865000
b111111111111111111 K
b111111111111111111 W
b1100 Q
b1100 V
b101101011111001001101101001100 T
b11011101110110000001011101110100 S
bx H
b100 I
14
#870000
04
#875000
b11111111111111111 K
b11111111111111111 W
b1101 Q
b1101 V
b101101011011101011110111001011 T
b11011101110110101110111100111101 S
bx H
b100 I
14
#880000
04
#885000
b1111111111111111 K
b1111111111111111 W
b1110 Q
b1110 V
b101101011001111100111011110100 T
b11011101110111000101101010110010 S
bx H
b100 I
14
#890000
04
#895000
b111111111111111 K
b111111111111111 W
b1111 Q
b1111 V
b101101011001000101011110000011 T
b11011101110111010001000001010001 S
bx H
b100 I
14
#900000
04
#905000
b0 K
b0 W
b10000 Q
b10000 V
b101101011000101001101111001001 T
b11011101110111010110101100011001 S
bx H
b100 I
14
#910000
04
#915000
0O
bx H
b100 I
14
#920000
04
#925000
b110010010000111111011010101001 K
b110010010000111111011010101001 W
1O
b0 Q
b0 V
b0 T
b1001101101110100111011011010000 S
bx H
b100 I
14
#930000
04
#935000
b11101101011000110011100000101 K
b11101101011000110011100000101 W
b1 Q
b1 V
b10110010010001011000100100110000 T
bx H
b100 I
14
#940000
04
#945000
b1111101011011011101011111100 K
b1111101011011011101011111100 W
b10 Q
b10 V
b10001011011010000100110111001000 T
b10100110110111010011101101101000 S
bx H
b100 I
14
#950000
04
#955000
b111111101010110111010100110 K
b111111101010110111010100110 W
b11 Q
b11 V
b1100001101100001111111011101110 T
b11001001101101110100111011011010 S
bx H
b100 I
14
#960000
04
#965000
b11111111101010101101110110 K
b11111111101010101101110110 W
b100 Q
b100 V
b1001000011110100001010100010011 T
b11010101111011010110111010110111 S
bx H
b100 I
14
#970000
04
#975000
b1111111111101010101011011 K
b1111111111101010101011011 W
b101 Q
b101 V
b111011000110110011111000101000 T
b11011010011101010001000000001000 S
bx H
b100 I
14
#980000
04
#985000
b111111111111101010111010 K
b111111111111101010111010 W
b110 Q
b110 V
b110100010001111001010110101000 T
b11011100010011011110100111111001 S
bx H
b100 I
14
#990000
04
#995000
b11111111111111111010101 K
b11111111111111111010101 W
b111 Q
b111 V
b110000110101100101111000000001 T
b11011101000111110000100001001111 S
bx H
b100 I
14
#1000000
04
#1005000
b1111111111111111111111 K
b1111111111111111111111 W
b1000 Q
b1000 V
b101111000111000001111111110001 T
b11011101100000001011010100001011 S
bx H
b100 I
14
#1010000
04
#1015000
b111111111111111111111 K
b111111111111111111111 W
b1001 Q
b1001 V
b101110001111101001111100111100 T
b11011101101011111101000100101010 S
bx H
b100 I
14
#1020000
04
#1025000
b11111111111111111111 K
b11111111111111111111 W
b1010 Q
b1010 V
b101101110011111100011101010100 T
b11011101110001101111000001111001 S
bx H
b100 I
14
#1030000
04
#1035000
b1111111111111111111 K
b1111111111111111111 W
b1011 Q
b1011 V
b101101100110000101010110011000 T
b11011101110100100110010001101010 S
bx H
b100 I
14
#1040000
04
#1045000
b111111111111111111 K
b111111111111111111 W
b1100 Q
b1100 V
b101101011111001001101101001100 T
b11011101110110000001011101110100 S
bx H
b100 I
14
#1050000
04
#1055000
b11111111111111111 K
b11111111111111111 W
b1101 Q
b1101 V
b101101011011101011110111001011 T
b11011101110110101110111100111101 S
bx H
b100 I
14
#1060000
04
#1065000
b1111111111111111 K
b1111111111111111 W
b1110 Q
b1110 V
b101101011001111100111011110100 T
b11011101110111000101101010110010 S
bx H
b100 I
14
#1070000
04
#1075000
b111111111111111 K
b111111111111111 W
b1111 Q
b1111 V
b101101011001000101011110000011 T
b11011101110111010001000001010001 S
bx H
b100 I
14
#1080000
04
#1085000
b0 K
b0 W
b10000 Q
b10000 V
b101101011000101001101111001001 T
b11011101110111010110101100011001 S
bx H
b100 I
14
#1090000
04
#1095000
0O
bx H
b100 I
14
#1100000
04
