Verilog_projects/FFT_VS_MATLAB/trigos.v
`timescale 1ns/1ps

// Simple LUT for arctangent values (Q1.31 fixed point)
module lut_arctan(
    input  wire [4:0] idx,       // 0..31
    output reg  [31:0] atan_val
);
    always @(*) begin
        case(idx)
            5'd0:  atan_val = 32'h3243F6A9; // atan(2^-0) ≈ 45 deg
            5'd1:  atan_val = 32'h1DAC6705; // atan(2^-1)
            5'd2:  atan_val = 32'h0FADBAFC; // atan(2^-2)
            5'd3:  atan_val = 32'h07F56EA6;
            5'd4:  atan_val = 32'h03FEAB76;
            5'd5:  atan_val = 32'h01FFD55B;
            5'd6:  atan_val = 32'h00FFFABA;
            5'd7:  atan_val = 32'h007FFFD5;
            5'd8:  atan_val = 32'h003FFFFF;
            5'd9:  atan_val = 32'h001FFFFF;
            5'd10: atan_val = 32'h000FFFFF;
            5'd11: atan_val = 32'h0007FFFF;
            5'd12: atan_val = 32'h0003FFFF;
            5'd13: atan_val = 32'h0001FFFF;
            5'd14: atan_val = 32'h0000FFFF;
            5'd15: atan_val = 32'h00007FFF;
            default: atan_val = 32'h0;
        endcase
    end
endmodule


// Iterative CORDIC for cos and sin
module cordic_cos #(
    parameter WIDTH = 32,
    parameter ITER  = 16       // Number of iterations
)(
    input  wire                 clk,
    input  wire                 rst,
    input  wire [WIDTH-1:0]     angle_in,  // Q1.31 fixed-point
    output reg  [WIDTH-1:0]     cos_out,   // Q1.31
    output reg  [WIDTH-1:0]     sin_out    // Q1.31
);

    // Scaling factor K ≈ 0.607252 (Q1.31)
    localparam [WIDTH-1:0] K = 32'h4DBA76D0;

    // Iteration registers
    reg [WIDTH-1:0] x, y, z;
    reg [4:0] i;
    reg busy;

    wire [WIDTH-1:0] atan_val;
    lut_arctan arctan_lookup(.idx(i[4:0]), .atan_val(atan_val));

    always @(posedge clk or posedge rst) begin
        if (rst) begin
            x       <= 0;
            y       <= 0;
            z       <= 0;
            i       <= 0;
            busy    <= 0;
            cos_out <= 0;
            sin_out <= 0;
        end else begin
            if (!busy) begin
                // Initialize vector
                x    <= K;
                y    <= 0;
                z    <= angle_in;
                i    <= 0;
                busy <= 1;
            end else if (i < ITER) begin
                // Rotation
                if (z[WIDTH-1] == 0) begin // z >= 0
                    x <= x - (y >>> i);
                    y <= y + (x >>> i);
                    z <= z - atan_val;
                end else begin
                    x <= x + (y >>> i);
                    y <= y - (x >>> i);
                    z <= z + atan_val;
                end
                i <= i + 1;
            end else begin
                // Done
                cos_out <= x;
                sin_out <= y;
                busy <= 0;
            end
        end
    end

endmodule

Verilog_projects/FFT_VS_MATLAB/trigos_tb.v
`timescale 1ns/1ps

module trigos_tb;

    reg clk;
    reg rst;
    reg [31:0] angle_in;
    wire [31:0] cos_out;
    wire [31:0] sin_out;

    // Instantiate the CORDIC module
    cordic_cos uut (
        .clk(clk),
        .rst(rst),
        .angle_in(angle_in),
        .cos_out(cos_out),
        .sin_out(sin_out)
    );

    // Clock generation: 10 ns period
    initial clk = 0;
    always #5 clk = ~clk;

    // Test stimulus
    initial begin
        // Initialize
        rst = 1;
        angle_in = 0;
        #20;
        rst = 0;

        // Test angles in Q1.31 format
        // 0 rad
        angle_in = 32'd0;
        #200;

        // pi/4 rad ~ 0.785398 in Q1.31
        angle_in = 32'd67108864; // approximate 2^31 * 0.785398 / pi
        #200;

        // pi/2 rad ~ 1.5708
        angle_in = 32'd134217728; 
        #200;

        // pi rad ~ 3.14159
        angle_in = 32'd268435456;
        #200;

        // 3*pi/2 rad ~ 4.71239
        angle_in = 32'd402653184;
        #200;

        // End simulation
        $finish;
    end

    // VCD dump
    initial begin
        $dumpfile("trigos_tb.vcd");
        $dumpvars(0, trigos_tb.uut);
    end

endmodule

Verilog_projects/FFT_VS_MATLAB/trigos_tb.vcd
$date
	Sun Dec 14 17:33:23 2025
$end
$version
	Icarus Verilog
$end
$timescale
	1ps
$end
$scope module trigos_tb $end
$scope module uut $end
$var wire 32 ! angle_in [31:0] $end
$var wire 1 " clk $end
$var wire 1 # rst $end
$var wire 32 $ atan_val [31:0] $end
$var parameter 32 % ITER $end
$var parameter 32 & K $end
$var parameter 32 ' WIDTH $end
$var reg 1 ( busy $end
$var reg 32 ) cos_out [31:0] $end
$var reg 5 * i [4:0] $end
$var reg 32 + sin_out [31:0] $end
$var reg 32 , x [31:0] $end
$var reg 32 - y [31:0] $end
$var reg 32 . z [31:0] $end
$scope module arctan_lookup $end
$var wire 5 / idx [4:0] $end
$var reg 32 0 atan_val [31:0] $end
$upscope $end
$upscope $end
$upscope $end
$enddefinitions $end
$comment Show the parameter values. $end
$dumpall
b100000 '
b1001101101110100111011011010000 &
b10000 %
$end
#0
$dumpvars
b110010010000111111011010101001 0
b0 /
b0 .
b0 -
b0 ,
b0 +
b0 *
b0 )
0(
b110010010000111111011010101001 $
1#
0"
b0 !
$end
#5000
1"
#10000
0"
#15000
1"
#20000
0"
0#
#25000
1(
b1001101101110100111011011010000 ,
1"
#30000
0"
#35000
b11101101011000110011100000101 $
b11101101011000110011100000101 0
b1 *
b1 /
b11001101101111000000100101010111 .
b1001101101110100111011011010000 -
1"
#40000
0"
#45000
b1111101011011011101011111100 $
b1111101011011011101011111100 0
b10 *
b10 /
b11101011011010000111000001011100 .
b100110110111010011101101101000 -
b1110100100101111011001000111000 ,
1"
#50000
0"
#55000
b111111101010110111010100110 $
b111111101010110111010100110 0
b11 *
b11 /
b11111011000101100010101101011000 .
b1001101101110100111011011010 -
b1111110010011110000000100010010 ,
1"
#60000
0"
#65000
b11111111101010101101110110 $
b11111111101010101101110110 0
b100 *
b100 /
b11000010111001100111111110 .
b11111001111011010110111010111000 -
b1111111100001011110101011101101 ,
1"
#70000
0"
#75000
b1111111111101010101011011 $
b1111111111101010101011011 0
b101 *
b101 /
b11111111000011001110111010001000 .
b1111001011100110101100110 -
b1101111111001110001010000000010 ,
1"
#80000
0"
#85000
b111111111111101010111010 $
b111111111111101010111010 0
b110 *
b110 /
b1000011001100001111100011 .
b11111110011001101001010011000110 -
b1101111111101100100001001101101 ,
1"
#90000
0"
#95000
b11111111111111111010101 $
b11111111111111111010101 0
b111 *
b111 /
b11001100100100101001 .
b1001100110110111001111 -
b1101011111111001010100000011010 ,
1"
#100000
0"
#105000
b1111111111111111111111 $
b1111111111111111111111 0
b1000 *
b1000 /
b11111111100011001100100101010100 .
b111111100110011100011111 -
b1101011111111000101101100111111 ,
1"
#110000
0"
#115000
b111111111111111111111 $
b111111111111111111111 0
b1001 *
b1001 /
b11111111110011001100100101010011 .
b100100100110101011000100 -
b1101011111111010101100110100110 ,
1"
#120000
0"
#125000
b11111111111111111111 $
b11111111111111111111 0
b1010 *
b1010 /
b11111111111011001100100101010010 .
b10111000110110000011000 -
b1101011111111011010001011011011 ,
1"
#130000
0"
#135000
b1111111111111111111 $
b1111111111111111111 0
b1011 *
b1011 /
b11111111111111001100100101010001 .
b10000010110110010110000 -
b1101011111111011011100111110110 ,
1"
#140000
0"
#145000
b111111111111111111 $
b111111111111111111 0
b1100 *
b1100 /
b1001100100101010000 .
b1100111110110011111001 -
b1101011111111011100001000100011 ,
1"
#150000
0"
#155000
b11111111111111111 $
b11111111111111111 0
b1101 *
b1101 /
b1100100101010001 .
b1110101010110011010101 -
b1101011111111011011111011100101 ,
1"
#160000
0"
#165000
b1111111111111111 $
b1111111111111111 0
b1110 *
b1110 /
b11111111111111101100100101010010 .
b1111100000110011000010 -
b1101011111111011011110100010000 ,
1"
#170000
0"
#175000
b111111111111111 $
b111111111111111 0
b1111 *
b1111 /
b11111111111111111100100101010001 .
b1111000101110011001100 -
b1101011111111011011111000001000 ,
1"
#180000
0"
#185000
b0 $
b0 0
b10000 *
b10000 /
b100100101010000 .
b1110111000010011010001 -
b1101011111111011011111010000000 ,
1"
#190000
0"
#195000
0(
b1110111000010011010001 +
b1101011111111011011111010000000 )
1"
#200000
0"
#205000
b110010010000111111011010101001 $
b110010010000111111011010101001 0
1(
b0 *
b0 /
b0 .
b0 -
b1001101101110100111011011010000 ,
1"
#210000
0"
#215000
b11101101011000110011100000101 $
b11101101011000110011100000101 0
b1 *
b1 /
b11001101101111000000100101010111 .
b1001101101110100111011011010000 -
1"
#220000
0"
b100000000000000000000000000 !
#225000
b1111101011011011101011111100 $
b1111101011011011101011111100 0
b10 *
b10 /
b11101011011010000111000001011100 .
b100110110111010011101101101000 -
b1110100100101111011001000111000 ,
1"
#230000
0"
#235000
b111111101010110111010100110 $
b111111101010110111010100110 0
b11 *
b11 /
b11111011000101100010101101011000 .
b1001101101110100111011011010 -
b1111110010011110000000100010010 ,
1"
#240000
0"
#245000
b11111111101010101101110110 $
b11111111101010101101110110 0
b100 *
b100 /
b11000010111001100111111110 .
b11111001111011010110111010111000 -
b1111111100001011110101011101101 ,
1"
#250000
0"
#255000
b1111111111101010101011011 $
b1111111111101010101011011 0
b101 *
b101 /
b11111111000011001110111010001000 .
b1111001011100110101100110 -
b1101111111001110001010000000010 ,
1"
#260000
0"
#265000
b111111111111101010111010 $
b111111111111101010111010 0
b110 *
b110 /
b1000011001100001111100011 .
b11111110011001101001010011000110 -
b1101111111101100100001001101101 ,
1"
#270000
0"
#275000
b11111111111111111010101 $
b11111111111111111010101 0
b111 *
b111 /
b11001100100100101001 .
b1001100110110111001111 -
b1101011111111001010100000011010 ,
1"
#280000
0"
#285000
b1111111111111111111111 $
b1111111111111111111111 0
b1000 *
b1000 /
b11111111100011001100100101010100 .
b111111100110011100011111 -
b1101011111111000101101100111111 ,
1"
#290000
0"
#295000
b111111111111111111111 $
b111111111111111111111 0
b1001 *
b1001 /
b11111111110011001100100101010011 .
b100100100110101011000100 -
b1101011111111010101100110100110 ,
1"
#300000
0"
#305000
b11111111111111111111 $
b11111111111111111111 0
b1010 *
b1010 /
b11111111111011001100100101010010 .
b10111000110110000011000 -
b1101011111111011010001011011011 ,
1"
#310000
0"
#315000
b1111111111111111111 $
b1111111111111111111 0
b1011 *
b1011 /
b11111111111111001100100101010001 .
b10000010110110010110000 -
b1101011111111011011100111110110 ,
1"
#320000
0"
#325000
b111111111111111111 $
b111111111111111111 0
b1100 *
b1100 /
b1001100100101010000 .
b1100111110110011111001 -
b1101011111111011100001000100011 ,
1"
#330000
0"
#335000
b11111111111111111 $
b11111111111111111 0
b1101 *
b1101 /
b1100100101010001 .
b1110101010110011010101 -
b1101011111111011011111011100101 ,
1"
#340000
0"
#345000
b1111111111111111 $
b1111111111111111 0
b1110 *
b1110 /
b11111111111111101100100101010010 .
b1111100000110011000010 -
b1101011111111011011110100010000 ,
1"
#350000
0"
#355000
b111111111111111 $
b111111111111111 0
b1111 *
b1111 /
b11111111111111111100100101010001 .
b1111000101110011001100 -
b1101011111111011011111000001000 ,
1"
#360000
0"
#365000
b0 $
b0 0
b10000 *
b10000 /
b100100101010000 .
b1110111000010011010001 -
b1101011111111011011111010000000 ,
1"
#370000
0"
#375000
0(
1"
#380000
0"
#385000
b110010010000111111011010101001 $
b110010010000111111011010101001 0
1(
b0 *
b0 /
b100000000000000000000000000 .
b0 -
b1001101101110100111011011010000 ,
1"
#390000
0"
#395000
b11101101011000110011100000101 $
b11101101011000110011100000101 0
b1 *
b1 /
b11010001101111000000100101010111 .
b1001101101110100111011011010000 -
1"
#400000
0"
#405000
b1111101011011011101011111100 $
b1111101011011011101011111100 0
b10 *
b10 /
b11101111011010000111000001011100 .
b100110110111010011101101101000 -
b1110100100101111011001000111000 ,
1"
#410000
0"
#415000
b111111101010110111010100110 $
b111111101010110111010100110 0
b11 *
b11 /
b11111111000101100010101101011000 .
b1001101101110100111011011010 -
b1111110010011110000000100010010 ,
1"
#420000
0"
b1000000000000000000000000000 !
#425000
b11111111101010101101110110 $
b11111111101010101101110110 0
b100 *
b100 /
b111000010111001100111111110 .
b11111001111011010110111010111000 -
b1111111100001011110101011101101 ,
1"
#430000
0"
#435000
b1111111111101010101011011 $
b1111111111101010101011011 0
b101 *
b101 /
b11000011001110111010001000 .
b1111001011100110101100110 -
b1101111111001110001010000000010 ,
1"
#440000
0"
#445000
b111111111111101010111010 $
b111111111111101010111010 0
b110 *
b110 /
b1000011010001100100101101 .
b101011001010000011000000110 -
b1101111110101111110010110010111 ,
1"
#450000
0"
#455000
b11111111111111111010101 $
b11111111111111111010101 0
b111 *
b111 /
b11010001111001110011 .
b111001001000110010110011100 -
b1101111110000100101000101111111 ,
1"
#460000
0"
#465000
b1111111111111111111111 $
b1111111111111111111111 0
b1000 *
b1000 /
b11111111100011010001111010011110 .
b1000000000111110101000111110 -
b1101111101101000000100010110100 ,
1"
#470000
0"
#475000
b111111111111111111111 $
b111111111111111111111 0
b1001 *
b1001 /
b11111111110011010001111010011101 .
b111100101000011011000110110 -
b1101111101111000000110010011110 ,
1"
#480000
0"
#485000
b11111111111111111111 $
b11111111111111111111 0
b1010 *
b1010 /
b11111111111011010001111010011100 .
b111010111000101100000110000 -
b1101111101111111101011010111001 ,
1"
#490000
0"
#495000
b1111111111111111111 $
b1111111111111111111 0
b1011 *
b1011 /
b11111111111111010001111010011011 .
b111010000000110100000111011 -
b1101111110000011010110111001111 ,
1"
#500000
0"
#505000
b111111111111111111 $
b111111111111111111 0
b1100 *
b1100 /
b1010001111010011010 .
b111001100100111000000000110 -
b1101111110000101001010111011100 ,
1"
#510000
0"
#515000
b11111111111111111 $
b11111111111111111 0
b1101 *
b1101 /
b10001111010011011 .
b111001110010110110000101111 -
b1101111110000100010001010110101 ,
1"
#520000
0"
#525000
b1111111111111111 $
b1111111111111111 0
b1110 *
b1110 /
b11111111111111110001111010011100 .
b111001111001110101001000000 -
b1101111110000011110100011101010 ,
1"
#530000
0"
#535000
b111111111111111 $
b111111111111111 0
b1111 *
b1111 /
b1111010011011 .
b111001110110010101100111001 -
b1101111110000100000010111011101 ,
1"
#540000
0"
#545000
b0 $
b0 0
b10000 *
b10000 /
b11111111111111111001111010011100 .
b111001111000000101010111101 -
b1101111110000011111011101100111 ,
1"
#550000
0"
#555000
0(
b111001111000000101010111101 +
b1101111110000011111011101100111 )
1"
#560000
0"
#565000
b110010010000111111011010101001 $
b110010010000111111011010101001 0
1(
b0 *
b0 /
b1000000000000000000000000000 .
b0 -
b1001101101110100111011011010000 ,
1"
#570000
0"
#575000
b11101101011000110011100000101 $
b11101101011000110011100000101 0
b1 *
b1 /
b11010101101111000000100101010111 .
b1001101101110100111011011010000 -
1"
#580000
0"
#585000
b1111101011011011101011111100 $
b1111101011011011101011111100 0
b10 *
b10 /
b11110011011010000111000001011100 .
b100110110111010011101101101000 -
b1110100100101111011001000111000 ,
1"
#590000
0"
#595000
b111111101010110111010100110 $
b111111101010110111010100110 0
b11 *
b11 /
b11000101100010101101011000 .
b1001101101110100111011011010 -
b1111110010011110000000100010010 ,
1"
#600000
0"
#605000
b11111111101010101101110110 $
b11111111101010101101110110 0
b100 *
b100 /
b11111011001000001011110010110010 .
b11001100000010010111011111100 -
b1111101000110000001011100110111 ,
1"
#610000
0"
#615000
b1111111111101010101011011 $
b1111111111101010101011011 0
b101 *
b101 /
b11111111000111110110100000101000 .
b10001101011111010110110001001 -
b1111110101100000010101000100110 ,
1"
#620000
0"
b10000000000000000000000000000 !
#625000
b111111111111101010111010 $
b111111111111101010111010 0
b110 *
b110 /
b1000111110011110110000011 .
b1101101110100010110000111000 -
b1111111001111011010011110010010 ,
1"
#630000
0"
#635000
b11111111111111111010101 $
b11111111111111111010101 0
b111 *
b111 /
b111110100001011001001 .
b1111101101110010001011010110 -
b1111111000001101011111011100010 ,
1"
#640000
0"
#645000
b1111111111111111111111 $
b1111111111111111111111 0
b1000 *
b1000 /
b11111111100111110100001011110100 .
b10000101101010011000001010011 -
b1111110111001110101000010011101 ,
1"
#650000
0"
#655000
b111111111111111111111 $
b111111111111111111111 0
b1001 *
b1001 /
b11111111110111110100001011110011 .
b10000001101100100100100000011 -
b1111110111110000000010111001101 ,
1"
#660000
0"
#665000
b11111111111111111111 $
b11111111111111111111 0
b1010 *
b1010 /
b11111111111111110100001011110010 .
b1111111101101100110100000001 -
b1111111000000000010000011110001 ,
1"
#670000
0"
#675000
b1111111111111111111 $
b1111111111111111111 0
b1011 *
b1011 /
b11110100001011110001 .
b1111110101110000110011111001 -
b1111111000001000001111010100100 ,
1"
#680000
0"
#685000
b111111111111111111 $
b111111111111111111 0
b1100 *
b1100 /
b1110100001011110010 .
b1111111001101110110101111100 -
b1111111000000100010001111000011 ,
1"
#690000
0"
#695000
b11111111111111111 $
b11111111111111111 0
b1101 *
b1101 /
b110100001011110011 .
b1111111011101101110110011110 -
b1111111000000010010010101010101 ,
1"
#700000
0"
#705000
b1111111111111111 $
b1111111111111111 0
b1110 *
b1110 /
b10100001011110100 .
b1111111100101101010110100111 -
b1111111000000001010010111011111 ,
1"
#710000
0"
#715000
b111111111111111 $
b111111111111111 0
b1111 *
b1111 /
b100001011110101 .
b1111111101001101000110101001 -
b1111111000000000110011000010100 ,
1"
#720000
0"
#725000
b0 $
b0 0
b10000 *
b10000 /
b11111111111111111100001011110110 .
b1111111101011100111110101001 -
b1111111000000000100011000101011 ,
1"
#730000
0"
#735000
0(
b1111111101011100111110101001 +
b1111111000000000100011000101011 )
1"
#740000
0"
#745000
b110010010000111111011010101001 $
b110010010000111111011010101001 0
1(
b0 *
b0 /
b10000000000000000000000000000 .
b0 -
b1001101101110100111011011010000 ,
1"
#750000
0"
#755000
b11101101011000110011100000101 $
b11101101011000110011100000101 0
b1 *
b1 /
b11011101101111000000100101010111 .
b1001101101110100111011011010000 -
1"
#760000
0"
#765000
b1111101011011011101011111100 $
b1111101011011011101011111100 0
b10 *
b10 /
b11111011011010000111000001011100 .
b100110110111010011101101101000 -
b1110100100101111011001000111000 ,
1"
#770000
0"
#775000
b111111101010110111010100110 $
b111111101010110111010100110 0
b11 *
b11 /
b1011000101100010101101011000 .
b1001101101110100111011011010 -
b1111110010011110000000100010010 ,
1"
#780000
0"
#785000
b11111111101010101101110110 $
b11111111101010101101110110 0
b100 *
b100 /
b11001000001011110010110010 .
b11001100000010010111011111100 -
b1111101000110000001011100110111 ,
1"
#790000
0"
#795000
b1111111111101010101011011 $
b1111111111101010101011011 0
b101 *
b101 /
b11111111001000100001000100111100 .
b100001010100101011000001101111 -
b1111011100000000000010001001000 ,
1"
#800000
0"
#805000
b111111111111101010111010 $
b111111111111101010111010 0
b110 *
b110 /
b1001000011110011010010111 .
b11101011101101011000001001101 -
b1111100100010101001100111001011 ,
1"
#810000
0"
#815000
b11111111111111111010101 $
b11111111111111111010101 0
b111 *
b111 /
b1000011110101111011101 .
b11111011010001101101010110100 -
b1111100000101001011111100001010 ,
1"
#820000
0"
b11000000000000000000000000000 !
#825000
b1111111111111111111111 $
b1111111111111111111111 0
b1000 *
b1000 /
b11111111101000011110110000001000 .
b100000011000010000010000110010 -
b1111011110101011110110101010101 ,
1"
#830000
0"
#835000
b111111111111111111111 $
b111111111111111111111 0
b1001 *
b1001 /
b11111111111000011110110000000111 .
b11111111001010010111001000101 -
b1111011111101100100111001011001 ,
1"
#840000
0"
#845000
b11111111111111111111 $
b11111111111111111111 0
b1010 *
b1010 /
b11110110000000110 .
b11111101001110011001100011110 -
b1111100000001100100000011110000 ,
1"
#850000
0"
#855000
b1111111111111111111 $
b1111111111111111111 0
b1011 *
b1011 /
b11111111111100011110110000000111 .
b11111110001100011010010101110 -
b1111011111111100101011100100100 ,
1"
#860000
0"
#865000
b111111111111111111 $
b111111111111111111 0
b1100 *
b1100 /
b11111111111110011110110000000110 .
b11111101101101011010011100100 -
b1111100000000100100111111101010 ,
1"
#870000
0"
#875000
b11111111111111111 $
b11111111111111111 0
b1101 *
b1101 /
b11111111111111011110110000000101 .
b11111101011101111010011000000 -
b1111100000001000100101101010101 ,
1"
#880000
0"
#885000
b1111111111111111 $
b1111111111111111 0
b1110 *
b1110 /
b11111111111111111110110000000100 .
b11111101010110001010010011110 -
b1111100000001010100100011001100 ,
1"
#890000
0"
#895000
b111111111111111 $
b111111111111111 0
b1111 *
b1111 /
b1110110000000011 .
b11111101010010010010010001001 -
b1111100000001011100011101111000 ,
1"
#900000
0"
#905000
b0 $
b0 0
b10000 *
b10000 /
b110110000000100 .
b11111101010100001110010010100 -
b1111100000001011000100000100110 ,
1"
#910000
0"
#915000
0(
b11111101010100001110010010100 +
b1111100000001011000100000100110 )
1"
#920000
0"
#925000
b110010010000111111011010101001 $
b110010010000111111011010101001 0
1(
b0 *
b0 /
b11000000000000000000000000000 .
b0 -
b1001101101110100111011011010000 ,
1"
#930000
0"
#935000
b11101101011000110011100000101 $
b11101101011000110011100000101 0
b1 *
b1 /
b11100101101111000000100101010111 .
b1001101101110100111011011010000 -
1"
#940000
0"
#945000
b1111101011011011101011111100 $
b1111101011011011101011111100 0
b10 *
b10 /
b11011010000111000001011100 .
b100110110111010011101101101000 -
b1110100100101111011001000111000 ,
1"
#950000
0"
#955000
b111111101010110111010100110 $
b111111101010110111010100110 0
b11 *
b11 /
b11110011101110101011010101100000 .
b1000100000000110010011111110110 -
b1101010111000000110001101011110 ,
1"
#960000
0"
#965000
b11111111101010101101110110 $
b11111111101010101101110110 0
b100 *
b100 /
b11111011101100000010010000000110 .
b110110101001110001101110001011 -
b1110011011000001100100001011100 ,
1"
#970000
0"
#975000
b1111111111101010101011011 $
b1111111111101010101011011 0
b101 *
b101 /
b11111111101011101100111101111100 .
b101111011100010000111100000110 -
b1110110110010110011101000010100 ,
1"
#980000
0"
#985000
b111111111111101010111010 $
b111111111111101010111010 0
b110 *
b110 /
b1101011101010010011010111 .
b101011101110101011010100110110 -
b1111000010001101100001010001100 ,
1"
#990000
0"
#995000
b11111111111111111010101 $
b11111111111111111010101 0
b111 *
b111 /
b101011101010101000011101 .
b101101100110111101000001000000 -
b1110111100101111101011110111000 ,
1"
#1000000
0"
#1005000
b1111111111111111111111 $
b1111111111111111111111 0
b1000 *
b1000 /
b1011101010101001001000 .
b101110100010101111111111101111 -
b1110111001111001010000000011000 ,
1"
#1010000
0"
#1015000
b111111111111111111111 $
b111111111111111111111 0
b1001 *
b1001 /
b11111111111011101010101001001001 .
b101111000000100011110010001111 -
b1110111000011100001010100011001 ,
1"
